widediaper/r_session
widediaper/version
widediaper
widediaper/parse
widediaper/utils
