Metadata-Version: 1.1
Name: widediaper
Version: 0.0.8
Summary: Simple, stable, easily debuggable R/Python piping
Home-page: http://github.com/endrebak/widediaper
Author: Endre Bakken Stovner
Author-email: endrebak@stud.ntnu.no
License: ['GPL-3.0']
Keywords: R,Statistics
Platform: UNKNOWN
Classifier: Programming Language :: Python :: 2.7
Classifier: Programming Language :: Python :: 3
Classifier: Development Status :: 2 - Pre-Alpha
Classifier: Environment :: Other Environment
Classifier: Intended Audience :: Developers
Classifier: Intended Audience :: Science/Research
Classifier: License :: OSI Approved :: GNU General Public License v3 (GPLv3)
Classifier: Operating System :: POSIX :: Linux
Classifier: Operating System :: MacOS :: MacOS X
Classifier: Topic :: Scientific/Engineering
Classifier: Topic :: Scientific/Engineering :: Interface Engine/Protocol Translator
Classifier: Topic :: Software Development :: Libraries :: Python Modules
